{"ECG_ID": "8527b5aa2b4a50336832f6dcf2419459", "win_start_time": "06:53:54", "reviewer_id": 8, "start_time": "", "episodes": [{"onset": 1, "rhythm_name": "NSR", "rhythm_code": 100, "offset": 958}, {"onset": 959, "rhythm_name": "WENCKEBACH", "rhythm_code": 1999, "offset": 1699}, {"onset": 1700, "rhythm_name": "NSR", "rhythm_code": 100, "offset": 2001}, {"onset": 2002, "rhythm_name": "WENCKEBACH", "rhythm_code": 1999, "offset": 2745}, {"onset": 2746, "rhythm_name": "NSR", "rhythm_code": 100, "offset": 3564}, {"onset": 3565, "rhythm_name": "WENCKEBACH", "rhythm_code": 1999, "offset": 4291}, {"onset": 4292, "rhythm_name": "NSR", "rhythm_code": 100, "offset": 6000}], "tag": "rev", "source_file": "", "onset_sample": -1}