{"ECG_ID": "af678b7885dbcf75bb9126790201696f", "win_start_time": "18:34:31", "reviewer_id": 3, "start_time": "", "episodes": [{"onset": 1, "rhythm_name": "NSR", "rhythm_code": 100, "offset": 259}, {"onset": 260, "rhythm_name": "JUNCTIONAL", "rhythm_code": 4000, "offset": 983}, {"onset": 984, "rhythm_name": "NSR", "rhythm_code": 100, "offset": 2123}, {"onset": 2124, "rhythm_name": "JUNCTIONAL", "rhythm_code": 4000, "offset": 2965}, {"onset": 2966, "rhythm_name": "NSR", "rhythm_code": 100, "offset": 3883}, {"onset": 3884, "rhythm_name": "JUNCTIONAL", "rhythm_code": 4000, "offset": 6000}], "tag": "rev", "source_file": "", "onset_sample": -1}